stackcollector/__init__.py
stackcollector/collector.py
stackcollector/devtools.py
stackcollector/stacksampler.py
stackcollector/visualizer.py
stackcollector/static/d3.flameGraph.css
stackcollector/static/d3.flameGraph.js
stackcollector/static/d3.js
stackcollector/static/d3.slider.css
stackcollector/static/d3.slider.js
stackcollector/static/d3.tip.v0.6.3.js
stackcollector/static/index.html
stackcollector-1.0.0.dist-info/LICENSE
stackcollector-1.0.0.dist-info/METADATA
stackcollector-1.0.0.dist-info/WHEEL
stackcollector-1.0.0.dist-info/top_level.txt
stackcollector-1.0.0.dist-info/RECORD
