Metadata-Version: 2.1
Name: stackcollector
Version: 1.0.0
Summary: UNKNOWN
Home-page: UNKNOWN
Author: Jakob Schmutz
Author-email: jakob@schmutz.co.uk
License: UNKNOWN
Platform: UNKNOWN
Classifier: Programming Language :: Python :: 3
Classifier: License :: OSI Approved :: MIT License
Classifier: Operating System :: OS Independent
Requires-Dist: requests (>=2.4.3)
Requires-Dist: flask (>=0.10.1)
Requires-Dist: click
Requires-Dist: dateparser
